libre_fastapi_jwt/__init__.py
libre_fastapi_jwt/auth_config.py
libre_fastapi_jwt/auth_jwt.py
libre_fastapi_jwt/config.py
libre_fastapi_jwt/exceptions.py
libre_fastapi_jwt-0.22.8.dist-info/LICENSE
libre_fastapi_jwt-0.22.8.dist-info/METADATA
libre_fastapi_jwt-0.22.8.dist-info/WHEEL
libre_fastapi_jwt-0.22.8.dist-info/RECORD
