Metadata-Version: 2.3
Name: libre-fastapi-jwt
Version: 0.22.8
Summary: Yet another fork of fast-jwt-auth
License: MIT
Author: Libre NZ
Author-email: github-support@libre.nz
Requires-Python: >=3.10.0,<4.0
Classifier: Environment :: Web Environment
Classifier: Intended Audience :: Developers
Classifier: License :: OSI Approved :: MIT License
Classifier: Operating System :: OS Independent
Classifier: Programming Language :: Python :: 3
Classifier: Programming Language :: Python :: 3.10
Classifier: Programming Language :: Python :: 3.11
Classifier: Programming Language :: Python :: 3.12
Classifier: Programming Language :: Python :: 3.13
Classifier: Topic :: Internet :: WWW/HTTP :: Dynamic Content
Classifier: Topic :: Software Development :: Libraries :: Python Modules
Requires-Dist: PyJWT (>=2.10.1,<3.0.0)
Requires-Dist: cryptography (>=44.0.1)
Requires-Dist: fastapi (>=0.115.8)
Requires-Dist: httpx (>=0.28.1)
Requires-Dist: poetry-plugin-up (>=0.9.0,<0.10.0)
Requires-Dist: pydantic-settings (>=2.7.1,<3.0.0)
Project-URL: Repository, https://github.com/LibreNZ/libre-fastapi-jwt
